pgdbtoolkit/__init__.py
pgdbtoolkit/__version__.py
pgdbtoolkit/async_db.py
pgdbtoolkit/base.py
pgdbtoolkit/common_utils.py
pgdbtoolkit/config.py
pgdbtoolkit/connection_pool.py
pgdbtoolkit/exceptions.py
pgdbtoolkit/log.py
pgdbtoolkit/migrations.py
pgdbtoolkit/sync_db.py
pgdbtoolkit/validation.py
pgdbtoolkit-0.1.18.dist-info/licenses/LICENSE
pgdbtoolkit-0.1.18.dist-info/METADATA
pgdbtoolkit-0.1.18.dist-info/WHEEL
pgdbtoolkit-0.1.18.dist-info/top_level.txt
pgdbtoolkit-0.1.18.dist-info/RECORD
