Metadata-Version: 2.4
Name: PgDbToolkit
Version: 0.1.18
Summary: A package for managing PostgreSQL database operations
Home-page: https://github.com/Inostroza7/PgDbToolkit
Author: Gustavo Inostroza
Author-email: gusinostrozar@gmail.com
Classifier: Programming Language :: Python :: 3
Classifier: License :: OSI Approved :: MIT License
Classifier: Operating System :: OS Independent
Requires-Python: >=3.8
License-File: LICENSE
Requires-Dist: aimanagertoolkit>=0.1.12
Requires-Dist: pgvector>=0.3.6
Requires-Dist: openpyxl>=3.1.5
Requires-Dist: pandas>=2.2.3
Requires-Dist: psycopg[binary]>=3.2.3
Requires-Dist: psycopg_pool>=3.2.6
Requires-Dist: python-dotenv>=1.0.1
Requires-Dist: pytest>=8.3.5
Requires-Dist: pytest-asyncio>=0.26.0
Dynamic: author
Dynamic: author-email
Dynamic: classifier
Dynamic: description
Dynamic: description-content-type
Dynamic: home-page
Dynamic: license-file
Dynamic: requires-dist
Dynamic: requires-python
Dynamic: summary
